lancstro/__init__.py
lancstro/base.py
lancstro/data/office_numbers.txt
lancstro/members/__init__.py
lancstro/members/staff.py
lancstro-0.0.2.data/scripts/favourite_object.py
lancstro-0.0.2.dist-info/LICENSE
lancstro-0.0.2.dist-info/METADATA
lancstro-0.0.2.dist-info/WHEEL
lancstro-0.0.2.dist-info/top_level.txt
lancstro-0.0.2.dist-info/RECORD
