Metadata-Version: 2.1
Name: lancstro
Version: 0.0.2
Summary: Package defining the Lancaster Observational Astronomy group
Home-page: https://github.com/mattpitkin/lancstro
Author: Matthew Pitkin
Author-email: m.pitkin@lancaster.ac.uk
License: MIT
Platform: UNKNOWN
Classifier: Intended Audience :: Science/Research
Classifier: License :: OSI Approved :: MIT License
Classifier: Natural Language :: English
Classifier: Programming Language :: Python
Classifier: Programming Language :: Python :: 3
Classifier: Programming Language :: Python :: 3.6
Classifier: Programming Language :: Python :: 3.7
Classifier: Programming Language :: Python :: 3.8
Classifier: Programming Language :: Python :: 3.9
Classifier: Topic :: Scientific/Engineering
Classifier: Topic :: Scientific/Engineering :: Astronomy
Classifier: Topic :: Scientific/Engineering :: Physics
Requires-Python: >=3.6
License-File: LICENSE
Requires-Dist: astropy
Requires-Dist: astroquery (>=0.4.3)
Requires-Dist: numpy
